{
  "main": {
    "id": "77b475dd4fe06242",
    "type": "split",
    "children": [
      {
        "id": "6de1aab265bf66d9",
        "type": "tabs",
        "children": [
          {
            "id": "e41e59ddb9ec1bf6",
            "type": "leaf",
            "state": {
              "type": "markdown",
              "state": {
                "file": "Pentesting/Active-Directory/Registry Helper.md",
                "mode": "source",
                "source": false
              },
              "icon": "lucide-file",
              "title": "Registry Helper"
            }
          },
          {
            "id": "f7ba31ba0c9e9f9a",
            "type": "leaf",
            "state": {
              "type": "markdown",
              "state": {
                "file": "Tools/Security_Tools/CrackMapExec_NetExec.md",
                "mode": "source",
                "source": false
              },
              "icon": "lucide-file",
              "title": "CrackMapExec_NetExec"
            }
          },
          {
            "id": "6f479f2bd1ef0b77",
            "type": "leaf",
            "state": {
              "type": "markdown",
              "state": {
                "file": "Tools/PowerShell/General_Help.md",
                "mode": "source",
                "source": false
              },
              "icon": "lucide-file",
              "title": "General_Help"
            }
          },
          {
            "id": "72e82fbe4d8f7053",
            "type": "leaf",
            "state": {
              "type": "markdown",
              "state": {
                "file": "Tools/Security_Tools/Impacket.md",
                "mode": "source",
                "source": false
              },
              "icon": "lucide-file",
              "title": "Impacket"
            }
          }
        ],
        "currentTab": 2
      }
    ],
    "direction": "vertical"
  },
  "left": {
    "id": "ce37c448dc8e2afd",
    "type": "split",
    "children": [
      {
        "id": "03102c204409c3c7",
        "type": "tabs",
        "children": [
          {
            "id": "ec848d11d3523c0f",
            "type": "leaf",
            "state": {
              "type": "file-explorer",
              "state": {
                "sortOrder": "alphabetical",
                "autoReveal": false
              },
              "icon": "lucide-folder-closed",
              "title": "Files"
            }
          },
          {
            "id": "9c0cd564eae2c86c",
            "type": "leaf",
            "state": {
              "type": "search",
              "state": {
                "query": "",
                "matchingCase": false,
                "explainSearch": false,
                "collapseAll": false,
                "extraContext": false,
                "sortOrder": "alphabetical"
              },
              "icon": "lucide-search",
              "title": "Search"
            }
          },
          {
            "id": "87a8868b6521f7f6",
            "type": "leaf",
            "state": {
              "type": "bookmarks",
              "state": {},
              "icon": "lucide-bookmark",
              "title": "Bookmarks"
            }
          }
        ]
      }
    ],
    "direction": "horizontal",
    "width": 300
  },
  "right": {
    "id": "a1330f2d86f5edd2",
    "type": "split",
    "children": [
      {
        "id": "4ebb9002dd6d2c84",
        "type": "tabs",
        "children": [
          {
            "id": "ae6a0f661e42159f",
            "type": "leaf",
            "state": {
              "type": "backlink",
              "state": {
                "file": "Tools/Golang/MoTWbypass.md",
                "collapseAll": false,
                "extraContext": false,
                "sortOrder": "alphabetical",
                "showSearch": false,
                "searchQuery": "",
                "backlinkCollapsed": false,
                "unlinkedCollapsed": true
              },
              "icon": "links-coming-in",
              "title": "Backlinks for MoTWbypass"
            }
          },
          {
            "id": "33a32e3da67e7ae9",
            "type": "leaf",
            "state": {
              "type": "outgoing-link",
              "state": {
                "file": "Tools/Golang/MoTWbypass.md",
                "linksCollapsed": false,
                "unlinkedCollapsed": true
              },
              "icon": "links-going-out",
              "title": "Outgoing links from MoTWbypass"
            }
          },
          {
            "id": "a9cf1dab136b65af",
            "type": "leaf",
            "state": {
              "type": "tag",
              "state": {
                "sortOrder": "frequency",
                "useHierarchy": true,
                "showSearch": false,
                "searchQuery": ""
              },
              "icon": "lucide-tags",
              "title": "Tags"
            }
          },
          {
            "id": "ee7a3f96073a3ebb",
            "type": "leaf",
            "state": {
              "type": "outline",
              "state": {
                "file": "Tools/Golang/MoTWbypass.md",
                "followCursor": false,
                "showSearch": false,
                "searchQuery": ""
              },
              "icon": "lucide-list",
              "title": "Outline of MoTWbypass"
            }
          }
        ],
        "currentTab": 2
      }
    ],
    "direction": "horizontal",
    "width": 300,
    "collapsed": true
  },
  "left-ribbon": {
    "hiddenItems": {
      "switcher:Open quick switcher": false,
      "graph:Open graph view": false,
      "canvas:Create new canvas": false,
      "daily-notes:Open today's daily note": false,
      "templates:Insert template": false,
      "command-palette:Open command palette": false,
      "markdown-importer:Open format converter": false,
      "publish:Publish changes...": false,
      "workspaces:Manage workspace layouts": false,
      "obsidian-git:Open Git source control": false
    }
  },
  "active": "6f479f2bd1ef0b77",
  "lastOpenFiles": [
    "Tools/Security_Tools/Password_Cracking.md",
    "Tools/Security_Tools/CrackMapExec_NetExec.md",
    "Pentesting/Active-Directory/Registry Helper.md",
    "Tools/Security_Tools/Impacket.md",
    "Tools/Security_Tools/Hydra.md",
    "Pentesting/Password Attacks.md",
    "Tools/Security_Tools/MetaSploit.md",
    "Tools/Security_Tools/Evil-Winrm.md",
    "Tools/Linux/RDP.md",
    "Tools/Linux/Priv_esc_cheatcodes.md",
    "Pentesting/5) Covering_CleaningUP",
    "Tools/Security_Tools/Shells & RevShells.md",
    "Pentesting/2) Enumeration/File_Transfering.md",
    "Pentesting/2) Enumeration/Web Basics.md",
    "Pentesting/2) Enumeration/Basics.md",
    "Pentesting/1)Recon/Osint.md",
    "Pentesting/4) Maintaining Access/File-Transfers/Windows Transfers.md",
    "Pentesting/4) Maintaining Access/File-Transfers/Misc Transfers.md",
    "Pentesting/4) Maintaining Access/File-Transfers/Linux Transfers.md",
    "Pentesting/4) Maintaining Access/File-Transfers",
    "2025-04-27.md",
    "Tools/Security_Tools/Nikto.md",
    "Pentesting/2) Enumeration/Certificates.md",
    "Tools/Security_Tools/Gobuster.md",
    "Challenges & CTFs/TryHackme/Daily Bugle.md",
    "Tools/Security_Tools/ffuf - Web Fuzzer.md",
    "Pentesting/2) Enumeration/DNS.md",
    "Pentesting/2) Enumeration/Databases.md",
    "Courses/HTB-Pentesting/nfs",
    "Courses/HTB-Pentesting/smb_results.txt",
    "Courses/HTB-Pentesting/results.txt",
    "Courses/HTB-Pentesting",
    "Courses/Pentesting",
    "img_assets/Pasted image 20240809162924.png",
    "Challenges & CTFs/TryHackme/Untitled",
    "Challenges & CTFs/TryHackme/Internal/Artifacts/jenkins_request.txt",
    "Challenges & CTFs/TryHackme/Internal/Artifacts/jenkins_request",
    "img_assets/Pasted image 20240809175042.png",
    "img_assets/Pasted image 20240809162933.png",
    "Untitled.canvas",
    "Pasted image 20240809163007.png",
    "Pasted image 20240809163013.png",
    "Pasted image 20240809175314.png"
  ]
}